LICENCE
README.md
setup.py
downcnpj/__init__.py
downcnpj/downcnpj.py
downcnpj.egg-info/PKG-INFO
downcnpj.egg-info/SOURCES.txt
downcnpj.egg-info/dependency_links.txt
downcnpj.egg-info/requires.txt
downcnpj.egg-info/top_level.txt