Metadata-Version: 2.1
Name: downcnpj
Version: 0.0.1
Summary: download cadastro nacional cnpj
Home-page: UNKNOWN
Author: Anthony Matheus
Author-email: anthonymatheusds@gmail.com.br
License: MIT License
Keywords: download cadastro nacional pessoa juridica cnpj
Platform: UNKNOWN
License-File: LICENCE
